aioroboremote/__init__.py
aioroboremote/deco.py
aioroboremote/library.py
aioroboremote/server.py
aioroboremote/internal/__init__.py
aioroboremote/internal/convert.py
aioroboremote/internal/interceptor.py
aioroboremote/internal/meta.py
aioroboremote/internal/view.py
aioroboremote-0.0.1.dist-info/LICENSE
aioroboremote-0.0.1.dist-info/METADATA
aioroboremote-0.0.1.dist-info/WHEEL
aioroboremote-0.0.1.dist-info/top_level.txt
aioroboremote-0.0.1.dist-info/RECORD
