Metadata-Version: 2.1
Name: aioroboremote
Version: 0.0.1
Summary: RobotFramework remote library implementation for Python's asyncio
Author-email: Anton Kondrachkov <sx91@protonmail.com>
License: MIT License
Project-URL: Homepage, https://github.com/SX91/aioroboremote
Project-URL: Repository, https://github.com/SX91/aioroboremote
Project-URL: Bug Tracker, https://github.com/SX91/aioroboremote/issues
Keywords: asyncio,robotframework,testing,testautomation,remoteinterface
Classifier: Development Status :: 4 - Beta
Classifier: Programming Language :: Python :: 3
Classifier: License :: OSI Approved :: MIT License
Classifier: Operating System :: OS Independent
Requires-Python: >=3.9
License-File: LICENSE
Requires-Dist: aiohttp (~=3.8.4)
Requires-Dist: aiohttp-xmlrpc (~=1.5.0)
